combined_config/__init__.py
combined_config/config.py
combined_config-0.1.0.dist-info/METADATA
combined_config-0.1.0.dist-info/WHEEL
combined_config-0.1.0.dist-info/RECORD
