Metadata-Version: 2.1
Name: combined-config
Version: 0.1.0
Summary: 
Home-page: https://github.com/Perfect5th/combined_config
License: LGPL-3.0-only
Author: Mitch Burton
Author-email: mitch@mitchellburton.ca
Maintainer: Mitch Burton
Maintainer-email: mitch@mitchellburton.ca
Requires-Python: >=3.8
Classifier: License :: OSI Approved :: GNU Lesser General Public License v3 (LGPLv3)
Classifier: Programming Language :: Python :: 3
Classifier: Programming Language :: Python :: 3.8
Classifier: Programming Language :: Python :: 3.9
Classifier: Programming Language :: Python :: 3.10
Classifier: Programming Language :: Python :: 3.11
Project-URL: Repository, https://github.com/Perfect5th/combined_config
